cli_tools/__init__.py
cli_tools/tools.py
JefvdA_python_clitools-0.0.3.dist-info/LICENSE
JefvdA_python_clitools-0.0.3.dist-info/METADATA
JefvdA_python_clitools-0.0.3.dist-info/WHEEL
JefvdA_python_clitools-0.0.3.dist-info/top_level.txt
JefvdA_python_clitools-0.0.3.dist-info/RECORD
