Metadata-Version: 2.1
Name: JefvdA_python_clitools
Version: 0.0.3
Summary: A python package which adds simple cli tools to your python project.
Home-page: https://github.com/JefvdA/python_clitools
Author: JefvdA
Author-email: jef.v.d.a@live.be
Project-URL: Bug Tracker, https://github.com/JefvdA/python_clitools/issues
Classifier: Programming Language :: Python :: 3
Classifier: License :: OSI Approved :: MIT License
Classifier: Operating System :: OS Independent
Requires-Python: >=3.6
License-File: LICENSE
